nanosense/README.md
nanosense/__init__.py
nanosense/activation_codes.enc
nanosense/icons.icns
nanosense/icons.ico
nanosense/icons.png
nanosense/image_1.jpg
nanosense/nanosense.py
nanosense/requirements.txt
nanosense/Clustering and Data Reduction/__init__.py
nanosense/Clustering and Data Reduction/main.py
nanosense/Combine Datasets and Files/__init__.py
nanosense/Combine Datasets and Files/heka_reader.py
nanosense/Combine Datasets and Files/main.py
nanosense/Data Reduction/icons.icns
nanosense/Data Reduction/main.py
nanosense/Data Reduction/.eggs/README.txt
nanosense/Data Reduction/.eggs/altgraph-0.17.4-py3.10.egg/EGG-INFO/LICENSE
nanosense/Data Reduction/.eggs/altgraph-0.17.4-py3.10.egg/EGG-INFO/PKG-INFO
nanosense/Data Reduction/.eggs/altgraph-0.17.4-py3.10.egg/EGG-INFO/RECORD
nanosense/Data Reduction/.eggs/altgraph-0.17.4-py3.10.egg/EGG-INFO/WHEEL
nanosense/Data Reduction/.eggs/altgraph-0.17.4-py3.10.egg/EGG-INFO/top_level.txt
nanosense/Data Reduction/.eggs/altgraph-0.17.4-py3.10.egg/EGG-INFO/zip-safe
nanosense/Data Reduction/.eggs/altgraph-0.17.4-py3.10.egg/altgraph/Dot.py
nanosense/Data Reduction/.eggs/altgraph-0.17.4-py3.10.egg/altgraph/Graph.py
nanosense/Data Reduction/.eggs/altgraph-0.17.4-py3.10.egg/altgraph/GraphAlgo.py
nanosense/Data Reduction/.eggs/altgraph-0.17.4-py3.10.egg/altgraph/GraphStat.py
nanosense/Data Reduction/.eggs/altgraph-0.17.4-py3.10.egg/altgraph/GraphUtil.py
nanosense/Data Reduction/.eggs/altgraph-0.17.4-py3.10.egg/altgraph/ObjectGraph.py
nanosense/Data Reduction/.eggs/altgraph-0.17.4-py3.10.egg/altgraph/__init__.py
nanosense/Data Reduction/.eggs/macholib-1.16.3-py3.10.egg/EGG-INFO/LICENSE
nanosense/Data Reduction/.eggs/macholib-1.16.3-py3.10.egg/EGG-INFO/PKG-INFO
nanosense/Data Reduction/.eggs/macholib-1.16.3-py3.10.egg/EGG-INFO/RECORD
nanosense/Data Reduction/.eggs/macholib-1.16.3-py3.10.egg/EGG-INFO/WHEEL
nanosense/Data Reduction/.eggs/macholib-1.16.3-py3.10.egg/EGG-INFO/entry_points.txt
nanosense/Data Reduction/.eggs/macholib-1.16.3-py3.10.egg/EGG-INFO/requires.txt
nanosense/Data Reduction/.eggs/macholib-1.16.3-py3.10.egg/EGG-INFO/top_level.txt
nanosense/Data Reduction/.eggs/macholib-1.16.3-py3.10.egg/EGG-INFO/zip-safe
nanosense/Data Reduction/.eggs/macholib-1.16.3-py3.10.egg/macholib/MachO.py
nanosense/Data Reduction/.eggs/macholib-1.16.3-py3.10.egg/macholib/MachOGraph.py
nanosense/Data Reduction/.eggs/macholib-1.16.3-py3.10.egg/macholib/MachOStandalone.py
nanosense/Data Reduction/.eggs/macholib-1.16.3-py3.10.egg/macholib/SymbolTable.py
nanosense/Data Reduction/.eggs/macholib-1.16.3-py3.10.egg/macholib/__init__.py
nanosense/Data Reduction/.eggs/macholib-1.16.3-py3.10.egg/macholib/__main__.py
nanosense/Data Reduction/.eggs/macholib-1.16.3-py3.10.egg/macholib/_cmdline.py
nanosense/Data Reduction/.eggs/macholib-1.16.3-py3.10.egg/macholib/dyld.py
nanosense/Data Reduction/.eggs/macholib-1.16.3-py3.10.egg/macholib/dylib.py
nanosense/Data Reduction/.eggs/macholib-1.16.3-py3.10.egg/macholib/framework.py
nanosense/Data Reduction/.eggs/macholib-1.16.3-py3.10.egg/macholib/itergraphreport.py
nanosense/Data Reduction/.eggs/modulegraph-0.19.6-py3.10.egg/EGG-INFO/LICENSE
nanosense/Data Reduction/.eggs/modulegraph-0.19.6-py3.10.egg/EGG-INFO/PKG-INFO
nanosense/Data Reduction/.eggs/modulegraph-0.19.6-py3.10.egg/EGG-INFO/RECORD
nanosense/Data Reduction/.eggs/modulegraph-0.19.6-py3.10.egg/EGG-INFO/WHEEL
nanosense/Data Reduction/.eggs/modulegraph-0.19.6-py3.10.egg/EGG-INFO/entry_points.txt
nanosense/Data Reduction/.eggs/modulegraph-0.19.6-py3.10.egg/EGG-INFO/requires.txt
nanosense/Data Reduction/.eggs/modulegraph-0.19.6-py3.10.egg/EGG-INFO/top_level.txt
nanosense/Data Reduction/.eggs/modulegraph-0.19.6-py3.10.egg/EGG-INFO/zip-safe
nanosense/Data Reduction/.eggs/py2app-0.28.7-py3.10.egg/EGG-INFO/LICENSE.txt
nanosense/Data Reduction/.eggs/py2app-0.28.7-py3.10.egg/EGG-INFO/PKG-INFO
nanosense/Data Reduction/.eggs/py2app-0.28.7-py3.10.egg/EGG-INFO/RECORD
nanosense/Data Reduction/.eggs/py2app-0.28.7-py3.10.egg/EGG-INFO/WHEEL
nanosense/Data Reduction/.eggs/py2app-0.28.7-py3.10.egg/EGG-INFO/entry_points.txt
nanosense/Data Reduction/.eggs/py2app-0.28.7-py3.10.egg/EGG-INFO/requires.txt
nanosense/Data Reduction/.eggs/py2app-0.28.7-py3.10.egg/EGG-INFO/top_level.txt
nanosense-1.3.0.dist-info/METADATA
nanosense-1.3.0.dist-info/WHEEL
nanosense-1.3.0.dist-info/entry_points.txt
nanosense-1.3.0.dist-info/top_level.txt
nanosense-1.3.0.dist-info/RECORD
