Metadata-Version: 2.4
Name: nanosense
Version: 1.3.0
Summary: A comprehensive package for solid state nanopore data analysis and visualization.
Author-email: Shankar Dutt <shankar.dutt@anu.edu.au>
License: MIT
Project-URL: Homepage, https://github.com/shankardutt/nanosense
Classifier: Programming Language :: Python :: 3
Classifier: License :: OSI Approved :: MIT License
Classifier: Operating System :: OS Independent
Requires-Python: >=3.10
Requires-Dist: PySide6
Requires-Dist: cryptography
Requires-Dist: matplotlib
Requires-Dist: neo
Requires-Dist: numpy
Requires-Dist: pyabf
Requires-Dist: scipy
Requires-Dist: joblib
Requires-Dist: bottleneck
Requires-Dist: ruptures
Requires-Dist: pywavelets
Requires-Dist: detecta
Requires-Dist: hmmlearn
Requires-Dist: factor_analyzer
Requires-Dist: scikit-learn
Requires-Dist: h5py
Requires-Dist: lmfit
Requires-Dist: seaborn
Requires-Dist: pandas
Requires-Dist: tabulate
Requires-Dist: sktime
Requires-Dist: lightgbm
Requires-Dist: torchvision
Requires-Dist: tensorflow
Requires-Dist: numexpr
Requires-Dist: uncertainties
Requires-Dist: pyqtgraph
Requires-Dist: pynvml
Requires-Dist: psutil
Requires-Dist: nvidia-ml-py3
